tirex/__init__.py
tirex/base.py
tirex/util.py
tirex/api_adapter/__init__.py
tirex/api_adapter/forecast.py
tirex/api_adapter/gluon.py
tirex/api_adapter/hf_data.py
tirex/api_adapter/standard_adapter.py
tirex/models/__init__.py
tirex/models/embedding.py
tirex/models/patcher.py
tirex/models/tirex.py
tirex/models/trainer.py
tirex/models/base/base_classifier.py
tirex/models/base/base_regressor.py
tirex/models/base/base_tirex.py
tirex/models/classification/__init__.py
tirex/models/classification/gbm_classifier.py
tirex/models/classification/linear_classifier.py
tirex/models/classification/rf_classifier.py
tirex/models/regression/__init__.py
tirex/models/regression/gbm_regressor.py
tirex/models/regression/linear_regressor.py
tirex/models/regression/rf_regressor.py
tirex/models/slstm/block.py
tirex/models/slstm/cell.py
tirex/models/slstm/layer.py
tirex_mirror-2025.12.23.dist-info/licenses/LICENSE
tirex_mirror-2025.12.23.dist-info/licenses/LICENSE_MIRROR.txt
tirex_mirror-2025.12.23.dist-info/licenses/NOTICE.txt
tirex_mirror-2025.12.23.dist-info/METADATA
tirex_mirror-2025.12.23.dist-info/WHEEL
tirex_mirror-2025.12.23.dist-info/top_level.txt
tirex_mirror-2025.12.23.dist-info/RECORD
