Metadata-Version: 2.4
Name: tirex-mirror
Version: 2025.12.23
Summary: Unofficial mirror of NX-AI/tirex for packaging
Author-email: Arpad Rozsas <rozsasarpi@gmail.com>
License: NXAI COMMUNITY LICENSE AGREEMENT
Project-URL: Repository, https://github.com/rozsasarpi/tirex-mirror
Project-URL: Issues, https://github.com/rozsasarpi/tirex-mirror/issues
Keywords: TiRex,xLSTM,Timeseries,Zero-shot,Deep Learning,Timeseries-Forecasting,Timeseries-Classification,Timeseries-Regression
Classifier: Programming Language :: Python :: 3
Classifier: Operating System :: OS Independent
Requires-Python: >=3.11
License-File: LICENSE
License-File: LICENSE_MIRROR.txt
License-File: NOTICE.txt
Requires-Dist: torch
Requires-Dist: huggingface-hub
Requires-Dist: numpy
Requires-Dist: scikit-learn
Provides-Extra: cuda
Requires-Dist: xlstm; extra == "cuda"
Requires-Dist: ninja; extra == "cuda"
Provides-Extra: notebooks
Requires-Dist: ipykernel; extra == "notebooks"
Requires-Dist: matplotlib; extra == "notebooks"
Requires-Dist: pandas; extra == "notebooks"
Requires-Dist: python-dotenv; extra == "notebooks"
Provides-Extra: plotting
Requires-Dist: matplotlib; extra == "plotting"
Provides-Extra: gluonts
Requires-Dist: gluonts; extra == "gluonts"
Requires-Dist: pandas; extra == "gluonts"
Provides-Extra: hfdataset
Requires-Dist: datasets; extra == "hfdataset"
Provides-Extra: test
Requires-Dist: fev>=0.6.0; extra == "test"
Requires-Dist: pytest; extra == "test"
Requires-Dist: aeon; extra == "test"
Provides-Extra: classification
Requires-Dist: lightgbm[scikit-learn]; extra == "classification"
Provides-Extra: regression
Requires-Dist: lightgbm[scikit-learn]; extra == "regression"
Provides-Extra: all
Requires-Dist: xlstm; extra == "all"
Requires-Dist: ninja; extra == "all"
Requires-Dist: ipykernel; extra == "all"
Requires-Dist: matplotlib; extra == "all"
Requires-Dist: pandas; extra == "all"
Requires-Dist: python-dotenv; extra == "all"
Requires-Dist: gluonts; extra == "all"
Requires-Dist: datasets; extra == "all"
Requires-Dist: pytest; extra == "all"
Requires-Dist: fev>=0.6.0; extra == "all"
Requires-Dist: scikit-learn; extra == "all"
Requires-Dist: lightgbm[scikit-learn]; extra == "all"
Dynamic: license-file
